<?xml version="1.0" encoding="UTF-8" ?>
<!DOCTYPE tiles-definitions PUBLIC
        "-//Apache Software Foundation//DTD Tiles Configuration 2.0//EN"
        "http://tiles.apache.org/dtds/tiles-config_2_0.dtd">
        
<tiles-definitions>

	<definition name="maindef" template="/templates/common-layout.jsp">
		<put-attribute name="title" value="title.template" />
		<put-attribute name="header" value="/templates/header.jsp" />
		<put-attribute name="menu" value="/templates/menu.jsp" />
		<put-attribute name="body" value="/templates/body.jsp"/>
		<put-attribute name="footer" value="/templates/footer.jsp" />
	</definition>
	
	<definition name="home.def" extends="maindef">
		<put-attribute name="title" value="title.home" />
		<put-attribute name="body" value="/pages/home.jsp" />
	</definition>
	
	<definition name="listeMembres.def" extends="maindef">
		<put-attribute name="title" value="title.listeMembres" />
		<put-attribute name="body" value="/pages/listeMembres.jsp" />
	</definition>
	
	<definition name="membreForm.def" extends="maindef">
		<put-attribute name="title" value="title.membreForm.def" />
		<put-attribute name="body" value="/forms/membreForm.jsp" />
	</definition>
	
	<definition name="listeParametrage.def" extends="maindef">
		<put-attribute name="title" value="title.listeParametrage" />
		<put-attribute name="body" value="/pages/parametrage.jsp" />
	</definition>
	
</tiles-definitions>